interfaces/__init__.py
interfaces/base.py
interfaces/compat.py
interfaces/exceptions.py
interfaces/spec.py
interfaces/typing.py
interfaces/util.py
strict_interfaces-0.1.2.dist-info/LICENSE
strict_interfaces-0.1.2.dist-info/WHEEL
strict_interfaces-0.1.2.dist-info/METADATA
strict_interfaces-0.1.2.dist-info/RECORD
