Metadata-Version: 2.1
Name: strict-interfaces
Version: 0.1.2
Summary: A new approach to interfaces in Python
Home-page: https://github.com/lig/python-interfaces
License: UNKNOWN
Keywords: python strict interfaces implemetation pep
Author: Serge Matveenko
Author-email: lig@countzero.co
Requires-Python: >=3.7
Classifier: Development Status :: 4 - Beta
Classifier: Intended Audience :: Developers
Classifier: License :: OSI Approved :: MIT License
Classifier: Operating System :: OS Independent
Classifier: Programming Language :: Python :: 3.7
Classifier: Programming Language :: Python :: 3.8
Classifier: Programming Language :: Python :: 3 :: Only
Classifier: Topic :: Software Development :: Libraries :: Python Modules
Classifier: Typing :: Typed
